padaleclib/__init__.py
padaleclib/collectionsutils.py
padaleclib/inpututils.py
padaleclib-0.0.1.dist-info/LICENSE.md
padaleclib-0.0.1.dist-info/METADATA
padaleclib-0.0.1.dist-info/WHEEL
padaleclib-0.0.1.dist-info/top_level.txt
padaleclib-0.0.1.dist-info/RECORD
