Metadata-Version: 2.1
Name: padaleclib
Version: 0.0.1
Summary: A small library with some useful tools
Home-page: 
Author: Dark KryU
Classifier: Development Status :: 2 - Pre-Alpha
Classifier: License :: OSI Approved :: MIT License
Classifier: Programming Language :: Python :: 3.12
Classifier: Operating System :: Microsoft :: Windows :: Windows 11
License-File: LICENSE.md
